handsome/__init__.py
handsome/boy/__init__.py
handsome/boy/mseeage.py
stephyoung-1.1.dist-info/METADATA
stephyoung-1.1.dist-info/WHEEL
stephyoung-1.1.dist-info/top_level.txt
stephyoung-1.1.dist-info/RECORD
