Metadata-Version: 2.1
Name: stephyoung
Version: 1.1
Summary: 陈晨，杨彬，冯锦兴
Author: Yangbin
License: UNKNOWN
Platform: UNKNOWN
